{
    "2025-01-16 20:43:12.005991": {
        "username": "Test",
        "message": "test"
    },
    "2025-01-16 20:43:26.231949": {
        "username": "Вітя",
        "message": "привіт світ"
    },
    "2025-01-16 20:43:34.210012": {
        "username": "ку-ку",
        "message": "бла-бла"
    },
    "2025-01-16 20:43:53.432333": {
        "username": "ваіфвавіа",
        "message": "віаіфвавіа"
    },
    "2025-01-16 18:47:31.662442": {
        "username": "докер",
        "message": "докер повідомлення"
    },
    "2025-01-16 18:47:43.299754": {
        "username": "тест",
        "message": "ура все працює"
    },
    "2025-01-16 20:48:25.693251": {
        "username": "раз",
        "message": "два-три"
    },
    "2025-01-20 21:56:52.659921": {
        "username": "привіт",
        "message": "світ!"
    }
}